{
  "schemaVersion": 1,
  "id": "momentum-combat-v2",
  "version": "1.0.0",
  "name": "Momentum Combat v2",
  "description": "Damage scales with player movement speed. Jumping attacks deal 1.5x, falling attacks deal 3x, standing still deals 0.5x, and sprinting deals 1.3x damage.",
  "authors": ["ali77sina"],
  "contact": {},
  "license": "MIT",
  "environment": "*",
  "entrypoints": {
    "main": ["com.orca.momentumcombat.MomentumCombatMod"]
  },
  "mixins": ["momentumcombat.mixins.json"],
  "depends": {
    "fabricloader": ">=0.16.0",
    "minecraft": "~1.21.1",
    "java": ">=21",
    "fabric-api": "*"
  }
}
